{
  "original_filename": "full_750.md",
  "《国际图联趋势报告2017年新进展》已发布": {
    "context1": "IFLA TREND   \nREPORT2017   \nUPDATE   \n\"Libraries,ascommunitybased institutions,canboth   \nshape,and beshaped by external forces.If we take the   \ntime to understand them,we can be pioneers in pushing for   \nstronger,fairer,andmoreparticipatorysocieties\" INSIGHTSFROMTHE TREND REPORT",
    "context2": "根据国际图联成员对这些问题的探讨回答，《国际图联趋势报告》在2016年更新了新进展，展现了部分精彩讨论内容。",
    "context3": "2017年12月20日，国际图联发布了《国际图联趋势报告2017年新进展》，带来了3个更进一步的专家意见。根据2017年国际图联主席会议上的探讨结果，《国际图联趋势报告2017年新进展》主要提出了以下3个问题：",
    "context4": "图书馆有一个重要使命,即让所有人获取到信息。这项工作在不断变化的世界中更显得至关重要，它能够让用户获知信息，提高自身生活水平，创建美好社区。而反过来说,图书馆也需要了解这些正在改变其所处环境的力量，以抓住当前机遇，规避风险。",
    "context5": "国际图联于2013年首次发布了《国际图联趋势报告》,由此开后了一个新的对话。《国际图联趋势报告》让图情界的每个人都能了解到诸多专家在社会、经济、技术发展趋势方面的看法，并提出一个问题：这些发展变化会如何影响他们的生活、工作和制度。",
    "context6": "图书馆如何将革命性的3D打印技术融入服务中？",
    "context7": "图书馆应该如何解决全民教育的迫切需求？",
    "context8": "网络虚假信息泛滥,图书馆如何发扬自身竞争优势？",
    "context9": "这些专家报告特别强调了风险与机遇。而更重要的是,这一系列报告推动了人们展开更多思考。国际图联欢迎成员们和其他各界人士阅读这些报告，由此展开反思，探讨图书馆可以做什么，或者需要做些什么。"
  }
}