{
  "original_filename": "full_5866.md",
  "我国图书馆个性化服务研究趋势分析 ?Trend Analysis on the Library-Personalized一Service Research in China": {
    "context1": "梁晓华",
    "context2": "(天津师范大学天津300074)",
    "context3": "摘要通过对198年以来我国“图书馆个性化服务”研究文献的多项特征进行统计分析，揭示该项研究的现状和特点，分析研究趋势，为我国学者开展此项研究提出点滴建议。",
    "context4": "关键词中国图书馆个性化服务文献计量学",
    "context5": "近年来，随着计算机技术和网络技术在图书馆服务工作中的广泛应用，图书馆的个性化服务应运而生，它是根据用户的不同需求而特别制定的服务，既能满足用户日益增长的个性化需求，又能缩小信息提供者与使用者之间的距离[1]。服务时空的个性化,使用户在适合自己的时间和地点获得服务;服务方式的个性化，使用户的个人爱好或需求特点得到满足;服务内容个性化,使用户各取所需,各得其所。自 1998 年 MyLibrary$\\textcircled{ a}$ NCState 在美国北卡罗莱纳州立大学图书馆建立以来,全世界有许多图书馆相继创立了MyLibrary 服务。近几年，我国中科院文献情报中心、清华大学图书馆等单位也开始Mylibrary系统的研究和建设[2]。这种为用户量身定做的“图书馆个性化服务\"（以下简称\"服务”）在我国还是一个正在成长着的新生事物。"
  },
  "1数据来源与统计方法": {
    "context1": "本文数据是笔者于2007年5月 $2 0 { \\sim } 3 1$ 日在国家科技部西南信息中心的《维普中文期刊数据库》中，通过传统的检索方法（期刊范围：全部期刊;年限： $1 9 8 9 \\sim 2 0 0 7$ ;检索入口：题名或关键词)以“图书馆\\*个性化服务”为检索式进行模糊检索，剔除一稿多投的重复内容，最终得到493篇“服务”研究论文，涉及到651名著者、344个著者单位、149 种期刊、1055 个关键词。所有的数据处理工作都是采用文献计量学方法，在个人电脑上利用 $\\operatorname { E x c e l } 2 0 0 3$ 进行的。"
  },
  "2调查结果与分析": {
    "context1": "2.1文献年代分布调查发现：我国的\"服务\"研究工作始于1998 年，各年度(1999 年除外)均有论文发表，论文篇次随年代分布情况如图1所示。",
    "context2": "由图1知，我国“服务\"研究几乎是与国外同期起步的，如果将之分成两个阶段的话， $1 9 9 8 { \\sim } 2 0 0 3$ 为初级阶段，这一阶段的特点是：年发表论文量较少，但是增长速度快，说明我国的图书情报人员对此项研究极为关注，有许多研究者迅速地投入到此项研究中来。此阶段的研究论文中，大多是对国外\"服务”系统的介绍，侧重理论引进与研究。 $2 0 0 4 { \\sim } 2 0 0 6$ 年是高潮阶段，有 $7 4 . 4 4 \\%$ 的论文是在此期间发表的，这一时期年发表论文数量超过百篇，但是涨幅趋缓。研究者对“服务”的研究更为具体、广泛、深入、细致，进入了技术层面的研究，不但引进国外的“服务”系统，而且经过改革创新后投入使用,逐步构建自身的“服务”系统，通过确定服务理念，强化服务意识，改进服务策略，完善服务措施，扩大服务范围，探索服务模式，区分服务层次，提高服务水准，把\"服务\"研究推向了高潮。另外，图1中并没有2007年发表的论文出现，说明《维普中文期刊数据库》的时滞最少是5个月，读者要查看最新的文献，还是要查相关的、比较重要的现刊。",
    "context3": "![](images/cc402f2c780de7beaac38b88b51b82e7d7be3cf47782550cce3e8451add4280d.jpg)  \n图1各年度\"服务\"研究论文篇次统计图",
    "context4": "2.2作者分布在这 493 篇论文中,共出现了651名著者，说明\"服务\"研究已成为图书情报界广大学者较为关注的课题之一,拥有一定规模的研究群体，他们是\"服务\"研究的主要力量。发表不同篇数论文的著者分布情况见表1。",
    "context5": "如果把发表两篇以上论文的作者视为核心作者，共有 46人(毛有桂、郭家义、游星雅发表3篇，贾红发表4篇)共发表论文97篇，占“服务\"研究论文总量的 $1 9 . 6 8 \\%$ 。另有 $9 2 . 9 3 \\%$ 的作者只发表一篇论文。说明核心作者偏少，研究队伍不够稳定，要想提高“服务\"研究水平，必须设法稳定研究队伍。",
    "context6": "表1发表不同篇数论文的著者统计表",
    "context7": "<table><tr><td>发文篇数</td><td>著者数</td><td>百分比(%)</td></tr><tr><td>1</td><td>605</td><td>92.934</td></tr><tr><td>2</td><td>42</td><td>6.452</td></tr><tr><td>3</td><td>3</td><td>0.461</td></tr><tr><td>4</td><td>1</td><td>0.154</td></tr><tr><td>合计</td><td>651</td><td>100</td></tr></table>",
    "context8": "2.3作者的合作情况论文作者合作度，既能表现该项研究每篇论文的平均作者数，又是该项研究论文作者合作研究程度的一项重要指标，合作度的高低直接影响研究论文的质量，“服务\"研究各年度的著者合作情况见表2。",
    "context9": "表2各年度作者合作发表情况统计表",
    "context10": "<table><tr><td>著者数/篇</td><td>1</td><td>2</td><td>3</td><td>4</td><td>5</td><td>6</td><td></td></tr><tr><td>年代 1998</td><td></td><td></td><td>不同著者数的论文篇次</td><td></td><td></td><td></td><td>合计 1</td></tr><tr><td>2000</td><td>1 2</td><td></td><td></td><td></td><td></td><td></td><td>2</td></tr><tr><td>2001</td><td>12</td><td>3</td><td></td><td></td><td></td><td></td><td>15</td></tr><tr><td>2002</td><td>22</td><td>6</td><td>1</td><td></td><td></td><td></td><td>29</td></tr><tr><td>2003</td><td>60</td><td>13</td><td>4</td><td></td><td>1</td><td>1</td><td>79</td></tr><tr><td>2004</td><td>78</td><td>30</td><td>7</td><td>2</td><td>1</td><td></td><td>118</td></tr><tr><td>2005</td><td>96</td><td>21</td><td>4</td><td></td><td>1</td><td></td><td>122</td></tr><tr><td>2006</td><td>103</td><td>13</td><td>10</td><td>1</td><td></td><td></td><td>127</td></tr><tr><td>总计</td><td>374</td><td>86</td><td>26</td><td>3</td><td>3</td><td>1</td><td>493</td></tr></table>",
    "context11": "由表2可了解到从2000 年开始有两名著者或多名著者合作发表的论文，其中绝大多数是两三名著者合著的，四名及四名以上著者合著的论文只占合著论文的 $5 . 8 8 \\%$ ，为了提高服务研究的水平，应该加强不同著者间的合作，由表2还可以得到“服务\"研究论文的合作度和合作率见表3。",
    "context12": "表3各年度合作度及合作率统计表",
    "context13": "<table><tr><td>年代</td><td>合作度</td><td>合作率(%)</td><td>年代</td><td>合作度</td><td>合作率(%)</td></tr><tr><td>1998</td><td>1</td><td>0.00</td><td>2003</td><td>1.38</td><td>24.05</td></tr><tr><td>2000</td><td>1</td><td>0.00</td><td>2004</td><td>1.46</td><td>33.90</td></tr><tr><td>2001</td><td>1.2</td><td>20.00</td><td>2005</td><td>1.27</td><td>22.32</td></tr><tr><td>2002</td><td>1.28</td><td>24.14</td><td>2006</td><td>1.28</td><td>18.90</td></tr></table>",
    "context14": "可见，从整体上来说，我国“服务\"研究论文的合作度和合作率处于上升趋势，说明著者的合作意识不断增强。但是平均作者合作度(1.33)低于图书情报学和档案学的平均合作度(1.385);平均合作率 $( 2 4 . 1 4 \\%$ )低于人文社会科学的平均合作率$( 2 6 . 9 \\% )$ ,与图书情报学和档案学的平均合作率 $( 2 9 . 3 \\%$ 相比，差距更大[3]。说明\"服务\"研究在著者合作方面还有很大潜力，加强研究者之间的合作，共同探讨，取长补短，定能提高研究水平。",
    "context15": "2.4作者所在地分布对作者所在地区的分布进行统计分析，可以了解各地区“服务”研究队伍的现状，揭示各地区的研究水平。",
    "context16": "由表4可见我国\"服务\"研究文献的作者遍及全国29 个省、市、自治区(美国出现一次，有6篇论文未标明著者所在地)，北京不愧是我国的文化教育中心，发挥了模范带头作用，在此项研究中处于领先水平，发文量居全国首位。前15个省市出现的频次占总量的 $8 1 . 9 \\%$ ，是高频出现的地区，也是我国\"服务”研究的核心地区，后13个省市出现的频次仅占总量的 $1 3 . 9 \\%$ ，相对处于劣势。说明\"服务\"研究的范围虽然很广泛，却呈现较强的地域性，进一步加强各地区之间的交流与合作，以后进带",
    "context17": "先进,可以大有作为。",
    "context18": "表4著者所在地出现频次统计表",
    "context19": "<table><tr><td>省(市)名称</td><td>出现频次</td><td>比率</td><td>省(市)名称</td><td>出现频次</td><td>比率</td></tr><tr><td>北京</td><td>68</td><td>0.104</td><td>江苏</td><td>55</td><td>0.084</td></tr><tr><td>湖北</td><td>49</td><td>0.075</td><td>湖南</td><td>48</td><td>0.074</td></tr><tr><td>广东</td><td>47</td><td>0.072</td><td>浙江</td><td>43</td><td>0.066</td></tr><tr><td>山东</td><td>36</td><td>0.055</td><td>上海</td><td>32</td><td>0.049</td></tr><tr><td>辽宁</td><td>28</td><td>0.043</td><td>河南</td><td>27</td><td>0.041</td></tr><tr><td>黑龙江</td><td>25</td><td>0.038</td><td>福建</td><td>24</td><td>0.037</td></tr><tr><td>天津</td><td>19</td><td>0.029</td><td>吉林</td><td>17</td><td>0.026</td></tr><tr><td>安徽</td><td>16</td><td>0.025</td><td>江西</td><td>14</td><td>0.021</td></tr><tr><td>陕西</td><td>14</td><td>0.021</td><td>四川</td><td>13</td><td>0.020</td></tr><tr><td>河北</td><td>11</td><td>0.017</td><td>山西</td><td>11</td><td>0.017</td></tr><tr><td>甘肃</td><td>9</td><td>0.014</td><td>重庆</td><td>9</td><td>0.014</td></tr><tr><td>广西</td><td>7</td><td>0.011</td><td>无</td><td>6</td><td>0.009</td></tr><tr><td>云南</td><td>5</td><td>0.008</td><td>贵州</td><td>5</td><td>0.008</td></tr><tr><td>内蒙古</td><td>5</td><td>0.008</td><td>宁夏</td><td>5</td><td>0.008</td></tr><tr><td>新疆</td><td>2</td><td>0.003</td><td>青海</td><td>1</td><td>0.002</td></tr><tr><td>美国</td><td>1</td><td>0.002</td><td>合计</td><td>652</td><td>1</td></tr></table>",
    "context20": "2.5著者机构分布在这 493 篇论文中,有7篇没有注明著者单位,注明著者单位的论文中，有337个著者单位共出现650 次，各著者机构出现频次分布情况见表5。",
    "context21": "表5著者机构分布统计表",
    "context22": "<table><tr><td>机构出现频次</td><td>机构数</td><td>比率</td><td>机构出现次数</td></tr><tr><td>无</td><td>7</td><td>0.0204</td><td>7</td></tr><tr><td>1</td><td>220</td><td>0.6395</td><td>220</td></tr><tr><td>2</td><td>47</td><td>0.1366</td><td>94</td></tr><tr><td>3</td><td>28</td><td>0.0814</td><td>84</td></tr><tr><td>4</td><td>17</td><td>0.0496</td><td>68</td></tr><tr><td>5</td><td>7</td><td>0.0203</td><td>35</td></tr><tr><td>6</td><td>8</td><td>0.0233</td><td>48</td></tr><tr><td>7</td><td>4</td><td>0.0116</td><td>28</td></tr><tr><td>8</td><td>1</td><td>0.0029</td><td>8</td></tr><tr><td>9</td><td>2</td><td>0.0058</td><td>18</td></tr><tr><td>10</td><td>1</td><td>0.0029</td><td>10</td></tr><tr><td>18</td><td>1</td><td>0.0029</td><td>18</td></tr><tr><td>19</td><td>1</td><td>0.0029</td><td>19</td></tr><tr><td>合计</td><td>344</td><td>1.0000</td><td>657</td></tr></table>",
    "context23": "从表5可知，有 $6 9 . 9 5 \\%$ 的著者单位只出现1次，仅有$7 . 2 7 \\%$ 的著者单位出现5次以上。在117篇合作发表的论文中，仅有 $2 8 . 5 8 \\%$ 为不同单位跨行业、跨系统、跨地域的合作研究论文，虽然这样合作发表的论文较少，但却开了一个好头，这种合作方式可以开拓思路、开阔眼界，有利于展开不同学术观点的交流和讨论，图书情报领域多人合作和多单位合作的研究项目太少，进一步加强不同单位研究者的合作力度，必将推动我国\"服务\"研究向纵深发展。",
    "context24": "2.6多产单位如果把发文量大于等于6的单位称为多产单位，共有18个单位，发表149 篇论文，占论文总数的 $2 2 . 6 8 \\%$ ，多产单位中，中国科学院、武汉大学、清华大学位居前三名，其后依次为北京理工大学、湖南科技大学、浙江大学、中山大学、上海交通大学等。调查同时发现：高等院校图书馆、信息管理院(系)、计算机科学工程系和文献情报中心是主要作者单位，发文量为449篇，占\"服务\"研究论文总量的 $9 1 . 0 8 \\%$ ，说明中国科学院和高等院校具有雄厚的研究实力和很高的研究水平，是“服务\"研究的骨干力量，有能力帮助、带动其他图书情报机构搞好“服务\"研究。",
    "context25": "2.7期刊分布这493篇\"服务\"研究论文，分别刊登在 149种期刊上，其中有175篇论文发表在 25 种核心期刊上，普通期刊的刊均发文量为2.56,核心期刊的刊均发文量为7,表明在核心期刊上发表的\"服务\"研究论文相对集中，图书情报工作者在此研究领域的研究水平和研究成果的影响力都比较高。按照布拉德福的方法进行统计，发表\"服务\"研究论文的篇次随期刊种数增加的趋势见图2。",
    "context26": "拟合曲线方程：",
    "context27": "$$\n\\mathrm { y } = 1 2 6 . 0 2 \\mathrm { l n } ( \\mathrm { x } ) + 6 0 . 0 4\n$$",
    "context28": "![](images/38b095bd7aba21e2ffbbce23602d7a2de233cc17d7487c2db4056c456a736ffb.jpg)  \n图2论文篇次随期刊种数增加分布图",
    "context29": "可见\"服务\"研究文献在各种期刊中的分布情况，基本符合布拉德福定律,那么，依据布拉德福定律进行分析，有 $5 5 . 5 8 \\%$ 的\"服务\"研究的论文发表在 $1 4 . 0 9 \\%$ 的期刊上，不妨称这些期刊为重要期刊(见表6)。",
    "context30": "表6“服务\"研究的重要期刊统计表",
    "context31": "<table><tr><td>刊名名称</td><td>核心期刊*</td><td>发文数量</td></tr><tr><td>科技情报开发与经济</td><td></td><td>42</td></tr><tr><td>现代情报</td><td>*</td><td>32</td></tr><tr><td>图书馆学研究</td><td></td><td>18</td></tr><tr><td>情报杂志</td><td>*</td><td>17</td></tr><tr><td>图书馆论坛</td><td>*</td><td>17</td></tr><tr><td>情报探索</td><td></td><td>14</td></tr><tr><td>图书馆</td><td>*</td><td>13</td></tr><tr><td>图书馆杂志</td><td>*</td><td>12</td></tr><tr><td>图书情报工作</td><td>*</td><td>11</td></tr><tr><td>农业图书情报学刊</td><td></td><td>10</td></tr><tr><td>现代图书情报技术</td><td>*</td><td>10</td></tr><tr><td>江西图书馆学刊</td><td></td><td>9</td></tr><tr><td>情报资料工作</td><td>*</td><td>9</td></tr><tr><td>河南图书馆学刊</td><td></td><td>8</td></tr><tr><td>情报科学</td><td>*</td><td>8</td></tr><tr><td>图书馆学刊</td><td></td><td>8</td></tr><tr><td>浙江高校图书情报工作</td><td></td><td>8</td></tr><tr><td>高校图书馆工作</td><td></td><td>7</td></tr><tr><td>图书馆工作与研究</td><td>*</td><td>7</td></tr><tr><td>图书馆建设</td><td>*</td><td>7</td></tr><tr><td>中国图书馆学报</td><td>*</td><td>7</td></tr></table>",
    "context32": "表6列出的21种重要期刊中,图书馆学11种、情报学6种、图书情报混合4种。根据《中文核心期刊要目总览》(北京大学出版社,2000年6月)确定图书馆学、情报学的核心期刊12种。这些在中国图书情报界威望很高的核心期刊，其\"服务\"研究的发文量远远领先于其他同类期刊，其权威性再一次从本项研究中得到印证。这些期刊发表的论文既有理论引进又有实践创新，作为本领域的技术指导类刊物，在“服务\"研究中起到了指导作用。",
    "context33": "2.8文献的关键词分布情况关键词是科技论文不可或缺的组成部分，是表达文献主题概念的术语，它是最直接反映论文主题内容的词或词组[5]。关键词选用数量是否恰当,标引是否准确,关系到文献被检索的准确性和被利用的效率，国家标准 $\\mathrm { ( G B ~ 7 7 1 3 ~ - ~ 8 7 ) }$ 规定：每篇文献选取 $3 { \\sim } 8$ 个关键词[6]。“服务\"研究论文关键词的标引量分布情况见表7。",
    "context34": "表7关键词的标引量分布情况统计表",
    "context35": "<table><tr><td>年代</td><td>n&lt;3</td><td>3≤n≤8</td><td>n&gt;8</td><td>合计</td></tr><tr><td>1998</td><td></td><td>1</td><td></td><td>1</td></tr><tr><td>2000</td><td></td><td>2</td><td></td><td>2</td></tr><tr><td>2001</td><td></td><td>15</td><td></td><td>15</td></tr><tr><td>2002</td><td></td><td>28</td><td>1</td><td>129</td></tr><tr><td>2003</td><td></td><td>68</td><td>11</td><td>79</td></tr><tr><td>2004</td><td></td><td>96</td><td>22</td><td>118</td></tr><tr><td>2005</td><td>3</td><td>85</td><td>34</td><td>122</td></tr><tr><td>2006</td><td>4</td><td>117</td><td>6</td><td>127</td></tr><tr><td>合计</td><td>7</td><td>412</td><td>74</td><td>493</td></tr><tr><td>比率</td><td>0.0142</td><td>0.8357</td><td>0.1501</td><td>1</td></tr></table>",
    "context36": "从表7可以看出，“服务”研究论文的关键词标引数量，只有 $8 3 . 5 7 \\%$ 达到了国家标准，尤其是 $2 0 0 2 { \\sim } 2 0 0 5$ 年,出现了关键词标引数量不达标率逐年增加的现象，是非常不应该的，我们的作者和编辑都应该严格执行国家标准，进一步规范论文的关键词标引数量。"
  },
  "3结论与建议": {
    "context1": "近时期，“图书馆个性化服务\"研究在我国图书情报界掀起了高潮，并且达到了较高研究水平，图书情报领域的核心期刊在\"服务\"研究中起到了重要的指导作用。此项研究在各种期刊中的论文分布情况,基本符合布拉德福定律，但是研究队伍中稳定学者实在太少，各个地区的发展也不均衡，研究呈现较强的地域性，要想继续提高研究水平，必须稳定研究队伍，加强研究者之间的合作,特别是加强不同单位、不同地区研究者之间的合作，以先进带后进，使此项研究在全国范围内健康发展，达到为读者提供个性化优质服务的目的。"
  },
  "参考文献": {
    "context1": "1刘明.个性化服务——图书馆服务的新阶段[J]·图书馆学刊，2006(1):16—17  \n2黄关君·个性化图书馆服务模型研究[J]·图书情报工作,2005(1):78-83  \n3 苏新宁·图书馆学情报学与文献学学术影响力研究报告( $2 0 0 0 -$ 2004)——基于CSSCI的分析[J]·情报学报,2006,25(2)：131—153  \n4中文核心期刊目录(2004 年版)[EB];http://202.194.143.1/new-home/xin-xi-fu-wu/2OO4zhongwen-hexin $\\mathrm { h t m }$ ,2006.9.15  \n5邱均平.文献计量学[M]·北京：科学技术文献出版社,1988. $4 4 0 -$ 446  \n6李鞠 $1 9 9 4 \\sim 2 0 0 4$ 年《中国土地科学》论文关键词统计分析[J]·中国土地科学,2005,19(4):51-55",
    "context2": "(责编：钧梅)"
  }
}