{
    "参考文献": {
        "context1": "References"
    },
    "[24]刘利，成栋，苏欣．意见领袖对旅游虚拟社区参与行为影响的实证研究—以大学生为例[．旅游学刊，2018，33(9):83-93.": "References",
    "[25]廖俊云，林晓欣，卫海英．虚拟品牌社区价值如何影响消费者持续参与：品牌知识的调节作用[]．南开管理评论，2019，22 (6):16-26.": {
        "context1": "References"
    },
    "β7]张德鹏，林萌菲，陈春峰，等．品牌社区中情感和关系会激发推荐吗？—顾客心理依附对口碑推荐意愿的影响研究．管理评论，2019，31（2)：155-168.": {
        "context1": "References"
    },
    "[40]阳长征．社交网络中用户体验效用对知识持续共享意愿影响研究[．现代情报，2020，40（3)：88-102.": {
        "context1": "References",
        "context2": "References",
        "context3": "References"
    },
    "[9]周桂林，何明升.行动者网络理论的困境及出路—以虚拟社区系统的社会建构为例[]．自然辩证法研究，2009，25(9):78-83.": {
        "context1": "References",
        "context2": "References",
        "context3": "References",
        "context4": "References",
        "context5": "References"
    },
    "51 ]": {
        "context1": "References",
        "context2": "References"
    }
}