{
    "参考文献": {
        "context1": "References"
    },
    "王居平．数字图书馆评价的理论和方法[M.合肥：安徽大学出版社，2008.": {
        "context1": "References"
    },
    "[9]胡琼芳，曾建勋．基于多共现的文献相关度判定研究．情报理论与实践，2010（8)：77-80，103.": {
        "context1": "References"
    },
    "[1] 庞弘，方曙．基于多重共现的可视化分析工具设计及其知识发现方法研究[]．图书情报知识，2012（2）：100-107.": "References",
    "[2]杜云生，黄梦，邱鹏君，等．基于共现分析的中国一东盟合著论文研究[.情报杂志，2014（3)：77-80，38.": {
        "context1": "References"
    },
    "[4]楚存坤，李韬．模糊聚类技术在文献自动分类系统中的应用．现代情报，2009（9)：166-168，172.": {
        "context1": "References",
        "context2": "References",
        "context3": "References"
    },
    "(上接第94页)": {
        "context1": "References",
        "context2": "References",
        "context3": "References"
    }
}