{
    "参考文献": "References",
    "1 ": {
        "context1": "References"
    },
    "4,31，42沈志宏，张晓林.关联数据及其应用现状综述．现代图书情报技术，2010（11)": "References",
    "5 WWW2008．Linked Data on th": {
        "context1": "References"
    },
    "6 ISWC2008.How to Publish L": {
        "context1": "References"
    },
    "9Martin Malmsten著，李静雯译.将图书馆目录纳入语义万维网.现代图书情报技术，2009(3)": "References",
    "10,27 Ed Summers等著，姚小乐，刘炜译.LCSH,SKOS和关联数据．现代图书情报技术，2009（3)": "References",
    "11 DC-2009.Semantic Interope": {
        "context1": "References"
    }
}