{
    "国内学科信息门户发展现状分析": "True",
    "Analysis on Present Situation of Domestic Subject Information Gateways": "True",
    "1国内学科信息门户发展现状": "True",
    "1.1 CSDL 学科信息门户群": "True",
    "1.2NSTL 热点门户": "True",
    "1.3武汉理工大学图书馆门户": "True",
    "1.4中国科学院武汉文献情报中心门户": "True",
    "1.5中国林业科学研究院科技信息所门户": "True",
    "2国内学科信息门户特点": "True",
    "2.1承建机构": "True",
    "2.2学科覆盖范围": "True",
    "2.3资源组织": "True",
    "2.3.1 分类法": "True",
    "2.3.2资源类型组织法": "True",
    "2.4元数据描述": "True",
    "2.4.1基于DC 并进行选择、扩展": "True",
    "2.4.2采用元数据量大": "True",
    "2.4.3使用特色元数据项": "True",
    "2.5软件系统": "True",
    "2.6附加服务": "True",
    "3国内学科信息门户建设中存在的主要问题": "True",
    "3.1学科信息门户资源组织体系不够完善": "True",
    "3.1.1学科分类体系存在的问题": "True",
    "3.1.2资源类型组织体系存在的问题": "True",
    "3.2检索功能单一，对检索缺乏相关主题词表的支持": "True",
    "3.3学科信息门户之间缺乏互操作": "True",
    "3.4缺少个性化的附加服务": "True",
    "4对国内学科信息门户建设的建议": "True",
    "4.1学科信息门户资源组织体系的完善": "True",
    "4.1.1学科分类浏览体系的完善": "True",
    "4.1.2资源类型浏览体系的完善": "True",
    "4.2优化学科信息门户的检索功能": "True",
    "4.2.1 提供基于词表的检索": "True",
    "4.2.2提供对网络资源检索的检索工具": "True",
    "4.3在完善已有服务的基础上，开展具有本门户特色的个性化服务": "True",
    "4.4加强门户之间的合作，实现互操作": "True",
    "参考文献": "References",
    "11 ": "References",
    "（上接第887页）": "False"
}