{
    "近五次我国全国国民阅读调查综述": "True",
    "[关键词]国民阅读调查推广机制": "True",
    "1近五次我国国民阅读调查数据分析": "True",
    "1.1关于阅读认知程度、综合阅读率的分析：阅读认知程度较高，综合阅读率上升": "True",
    "1.2关于传统纸质媒介阅读率、数字阅读方式接触率的分析：图书阅读率平稳上升，数字化阅读接触率上升迅速": "True",
    "1.3关于各种形式载体阅读量的分析：报纸阅读量最高，电子书阅读量上升": "True",
    "1.4关于传统媒介与新兴媒介接触时长的分析：传统媒介接触时长下降，新兴媒介接触时长增加": "True",
    "手机阅读接触时长增幅最快。": "True",
    "从第七次到第十次的四次调查分析的总体情况": "True",
    "看，传统媒介的阅读时长呈缓慢下降趋势，新兴媒介的阅读接触时长呈增长趋势，参见表5和图4。": "True",
    "1.5关于国民数字化阅读方式的分析：网络在线阅读和手机阅读成为主流": "True",
    "1.6关于上网、上网从事相关活动等的分析：纸质读物是阅读倾向的首选": "True",
    "1.7关于图书、期刊、数字媒体等价格承受能力的分析：传统媒介价格承受力增加，数字媒体价格承受力下降": "True",
    "1.8关于个人阅读评价、举办阅读活动的分析：国民认为自己阅读量较少，六成国民希望举办阅读活动": "True",
    "1.9关于未成年人阅读情况的分析：阅读率与阅读量均超过成年人": "True",
    "面，未成年人的人均图书阅读量也超过了 $1 8 \\sim 7 0$ 周岁成年人。": "True",
    "2我国国民阅读行为檀变的原因分析": "True",
    "2.1图书阅读率平稳缓慢上升，纸质阅读仍是国民偏好的主流阅读形式": "True",
    "2.2各媒介综合阅读率保持稳步上升趋势": "True",
    "2.3数字阅读发展迅猛、增势强于传统阅读，网络在线阅读和手机阅读是数字阅读的主流": "True",
    "3我国国民阅读推广机制建设的对策": "True",
    "3.1政府主导推动国民阅读": "True"
}