{
    "高校图书馆人才队伍建设的回顾与对策": "True",
    "由《普通高等学校图书馆规程》（修订）谈起": "True",
    "李岩": "False",
    "1概述": "True",
    "2职称（学位）和学历是高校图书馆人才素质的基本要求": "True",
    "3高校图书馆管理人才和专业人才队伍建设回顾": "True",
    "3.1高校图书馆馆长、副馆长任职的三个时期": "True",
    "3.1.1 工农兵担任馆长、副馆长时期": "True",
    "3.1中国箱岗科专家根图书馆馆长n副馆长时期38": "False",
    "3.1.3其它学科和图书馆学科专家担任馆长、副馆长时期": "True",
    "3.2高校图书馆专业人员的学历状况": "True",
    "4关于加强图书馆人才队伍建设的对策": "True",
    "4.1关于管理人才": "True",
    "4.2关于专业技术人才": "True",
    "[参考文献]": "References",
    "A Review on and the Strategy for Personnel Training in University Libraries Starting our talk with “Rules for University Libraries”": "False"
}