{
    "大移动服务采纳行为实证研究综述：从2G到3GA Review for Adoption ofM obile Services. from 2G to 3G": "True",
    "1文献的选取及概况": "True",
    "理论模型的创新贡献度并不是很高。": "False",
    "2分析框架": "True",
    "2.1 研究主题对研究主题的分析，能够帮助": "True",
    "2.2 理论基础IS采纳研究的一个特点就是理论基础丰富，TAM、TRA、TPB等经典理论模型在不同 IS领域和不同的地域得到了广泛的检验。": "True",
    "2.3 研究情景情景": "True",
    "2.4 研究方法研究方法体现了一个领域内的研究成熟度。": "True",
    "2.5 影响因素影响移动服务采纳因素及其路径关系": "True",
    "3移动服务采纳领域研究现状分析": "True",
    "3.1 研究主题": "True",
    "3.2 理论基础移动服务作为电子商务的一个扩展，": "True",
    "3.3 研究情景从研究情景来看，绝大多数的文献(共69篇占 $9 3 . ~ 2 \\%$ )": "True",
    "3.4 研究方法实证研究方法的广泛应用说明了": "True",
    "3.5 影响因素由于信息系统采纳具有众多的理论模型从不同视角对采纳过程加以解释，": "True",
    "4结论及局限": "True",
    "4.1 结论通过对移动服务采纳实证研究文献的梳理和分析，": "True",
    "4.2 局限": "True",
    "参考文献": "References",
    "（上接第165页）": "False"
}