{
    "新信息环境下电子书馆配商经营模式分析与展望*": "True",
    "薛春燕 (南京大学金陵学院图书馆江苏 南京 210089)": "True",
    "[关键词]电子书馆配商电子书采购移动阅读经营模式高校图书馆联盟": "True",
    "1我国主要的电子书馆配商简介": "True",
    "26家电子书馆配商的对比分析": "True",
    "2.1图书品种和数量对比": "True",
    "2.2电子书阅读体验对比": "True",
    "2.3阅读平台对比": "True",
    "2.4销售方式与使用权限对比": "True",
    "2.5业务可持续性对比": "True",
    "3读者和图书馆对电子书的需求分析": "True",
    "3.1读者对电子书的需求": "True",
    "3.2图书馆对电子书的需求": "True",
    "4电子书馆配业务存在的问题": "True",
    "4.1资源重复严重,电子书馆配商互补性不足。": "True",
    "4.2专业性、学术类电子书品种不足": "True",
    "4.3打包式销售的不合理性": "True",
    "5高校图书馆的应对策略": "True",
    "5.1 立足读者需求,明确": "True",
    "5.2采用馆配双模式互补,避免重复建设,充分有效使用建设经费。": "True",
    "5.3建立以高校图书馆联盟为基础的专业电子书馆配模式": "True",
    "注释": "True",
    "参考文献：": "References",
    "[作者简介]": "False",
    "(上接第30页)": "False"
}