{
    "中国图书馆学情报学期刊发展现状与展望 \\*": "True",
    "An Investigation into the Development of Chinese Library and Information Science Journals": "True",
    "1国内外图书馆学情报学期刊产生与发展历程": "True",
    "1.1国外图书馆学情报学期刊的产生与发展": "True",
    "1.2国内图书馆学情报学期刊的产生与发展": "True",
    "2国内外图书馆学情报学期刊发展现状": "True",
    "2.1国内图书馆学情报学期刊发展现状": "True",
    "2.1.1 调研概况为掌握": "True",
    "2.1.2 调研结果—一全国图书馆学情报学期刊名称一览表": "True",
    "第48卷第11期2004年11月": "False",
    "2.1.3 调研数据统计及分析在展开具体的问卷统计及分析论述之前，需要说明的": "True",
    "2.2国外图书馆学情报学期刊抽样分析": "True",
    "3.1.3 期刊的经营有待规范化和专业化国外的学术期刊大都由规模宏大、实力强盛的出版社出版发行，而": "True",
    "3.2展望": "True",
    "参考文献：": "References",
    "3国内外对比思考及展望": "True",
    "3.1国内外对比思考": "True",
    "3.1.1 学术水平有待提高一方面,期刊的学术水平": "True",
    "3.1.2官方色彩浓厚,统一由政府管理期刊的“出身门": "True"
}