{
    "·管理论坛·": "False",
    "科学数据开放政策研究现状分析及未来研究动向评判": "True",
    "A Literature Review on Research Status and Developing Trend of Open Research Data Policy": "True",
    "1国内研究现状分析": "True",
    "1.1建立开放科学数据政策保障机制的理论性研究": "True",
    "1.2针对国内外各类科学数据开放共享政策的调查研究": "True",
    "1.3科学数据开放政策利益主体的开放共享行为研究": "True",
    "1.4制定开放科学数据相关知识产权政策法律问题的研究": "True",
    "1.5基于政策文本分析的科学数据开放政策实证研究": "True",
    "2国外研究现状分析": "True",
    "2.1制定科学数据开放政策的理论探讨与实践研究": "True",
    "2.2科学数据开放政策利益主体的开放共享行为研究": "True",
    "2.3面向科学数据开放政策利益主体的开放共享服务研究": "True",
    "2.4针对专业领域科学数据开放政策的政策分析研究": "True",
    "2.5基于政策文本分析的科学数据开放政策实证研究": "True",
    "3国内外研究现状的比较分析": "True",
    "4我国未来研究动向评判": "True",
    "4.1各类科学数据开放政策的调查与比较分析": "True",
    "4.2科学数据开放政策多个利益主体的博弈分析": "True",
    "4.3基于多学科方法的科学数据开放政策文本分析": "True",
    "4.4各类科学数据开放政策的政策协同研究": "True",
    "4.5科学数据开放政策的政策分析与评估研究": "True",
    "5结论": "True",
    "参考文献": "References",
    "[1]陈劲，陈钰芬．企业技术创新绩效评价指标体系研究[．科学学与科学技术管理，2006，(3)：86-91.": "References",
    "(上接第170页)": "False"
}