{
    "我国高校学科馆员制度实施十年回顾": "True",
    "1我国高校学科馆员制度产生概况": "True",
    "2我国高校确立学科馆员制度的现实意义": "True",
    "2.1体现了专业图书馆发展的必然趋势，是适应时代要求的服务模式": "True",
    "2.2创新了图书馆服务方式，有利于提供快捷便利的学科信息导航服务": "True",
    "2.3促进了图书馆服务向纵深发展，为提高服务水平创造了条件": "True",
    "2.4为重点教学、科研提供了更多的信息支持和技术保障": "True",
    "3目前我国高校实施学科馆员制度上存在的问题": "True",
    "3.1缺乏高素质、高质量的复合型人才": "True",
    "3.2缺乏有效的激励机制及管理机制": "True",
    "3.3缺乏充分的制度保障": "True",
    "3.4缺乏严格的职业资格认证": "True",
    "3.5发展过快，多数高校图书馆尚不存在学科馆员生存条件": "True",
    "4完善我国高校学科馆员制度有效措施与途径": "True",
    "4.1完善学科馆员服务质量考核评价体系": "True",
    "4.2重视人才资源的开发和利用": "True",
    "4.3提高科研意识，提供信息资源导航服务": "True",
    "4.4循序渐进，创造学科馆员的生存环境": "True",
    "4.5培养、提高学科馆员的综合素质": "True",
    "4.6完善鼓励竞争与创新的激励机制": "True",
    "5结语": "True",
    "[参考文献]": "References",
    "A Review of 10-Year Implementation of Subject Librarian System in University Library of China": "False"
}