{
    "国内网络信息资源保存研究进展": "True",
    "■ 陈萌": "True",
    "国内WA实践的兴起与发展": "True",
    "陈萌.国内网络信息资源保存研究进展": "References",
    "2国内WA研究的主要内容": "True",
    "2.1 文献统计": "True",
    "2.2主题研究": "True",
    "2.2.1 Web资源保存过程中面临的问题和挑战": "True",
    "2.2.2 国外项目的介绍与评析对国外WA项目的介绍与评析遍及整个国内WA研究历史。": "True",
    "2.2.3 责任体系研究初期,学者": "True",
    "2.2.4 Web资源的采集、保存、访问与使用在Web归档保存过程中，Web 采集、Web Archive的保存、WebArchive的访问和使用就是一个系统化的WebArchive研究框架。": "True",
    "2.3总结": "True",
    "3 未来研究方向": "True",
    "3.1责任主体的网络协作": "True",
    "3.2特定责任主体的保存研究": "True",
    "3.3采集的深化": "True",
    "3.4大数据下的存储和内容访问与管理": "True",
    "3.5多元化的利用形式": "True",
    "参考文献：": "References",
    "Progress of Domestic Research in Web Archive": "False"
}