{
    "美国公共图书馆老年服务现状及对我国的后示\\*": "True",
    "■肖雪周静": "True",
    "1文献回顾": "True",
    "2美国公共图书馆老年服务研究设计": "True",
    "3美国公共图书馆老年服务的现状分析": "True",
    "3.1服务理念分析": "True",
    "美国公共图书馆老年服务现状及对我国的后示": "False",
    "3.2服务指南分析": "True",
    "总体而言，美国图书馆老年服务指南文件具有两个": "True",
    "3.3服务项目分析": "True",
    "3.4服务工作分析": "True",
    "4 美国公共图书馆老年服务对我国的后示": "True",
    "4.1转换服务观念,深入了解老年用户": "True",
    "4.2完善服务指南和法规，制定服务规划": "True",
    "4.3明确服务重心，结合变化扩展服务内容": "True",
    "4.4注重社会合作，积极参与国家老年事务": "True",
    "4.5重视并充分发挥图书馆协会的作用": "True",
    "参考文献：": "References",
    "肖雪周静": "False",
    "58 ] Cahalan B.Aging creativ": "References",
    "Status Quo of American Public Library Services to the Old and the Implications": "False",
    "1 Department of Information": "False",
    "《图书情报工作网刊》改名《知识管理论坛》": "False"
}