{
    "评述美国NDIIP数字化保存结构": "False",
    "The Commentary on the Digital Preservation Architecture in America NDIIPP": "False",
    "1NDIIPP的发起及实施": "True",
    "20.2版保存结构的产生": "True",
    "3系统功能设计[3]": "True",
    "3.1整体结构及术语的变化": "True",
    "3.2底层": "True",
    "3.3中间层": "True",
    "·生命周期管理": "True",
    "3.4上层": "True",
    "4保存机构之间的连接": "True",
    "5NDIIPP对我国的借鉴意义": "True",
    "参考文献：": "References",
    "1 LeFurgy W. Building preservation partnerships: The Library ofCongress National digital information infrastructure andpreservation program.[2006-02-27].http://www.ndiipp.uinc.edu/idex.php?": "References"
}