{
    "国内公共图书馆创客空间发展现状调查研究龚雪竹": "True",
    "【摘要】文章选取公共图书馆作为研究对象，从创客空间构造、工具选择、活动类型、网页设计、网站服务导航、创客信息服务等方面进行梳理，论述图书馆创客服务的特点，研究创客空间建设的实施策略，推出符合双创时代要求的创客空间模式及服务模式。": "True",
    "【关键词】创客空间公共图书馆大众创业万众创新": "True",
    "1数据选取": "True",
    "2创客空间建造情况": "True",
    "对各部分进行统计分析。": "True",
    "2.1开放时间": "True",
    "2.2空间构造": "True",
    "2.3工具选择": "True",
    "2.4活动内容": "True",
    "3国内创客空间实施建议": "True",
    "3.1创新和创业的功能区分": "True",
    "3.2建立创客空间工具使用标准": "True",
    "3.3建设创客空间信息网站": "True",
    "3.4开展多样的创客活动": "True",
    "4结语": "True",
    "注释": "References",
    "12 ]百度．创业者[EB/OL]. $[ 2 0 1 7 - 0 6 - 0 8 ]$ http": "References"
}