{
    "面向传承和传播的非遗数字资源描述与语义揭示研究综述": "True",
    "1引言": "True",
    "2非遗资源数字化现状": "True",
    "3 非遗数字资源描述及标注方法研究": "True",
    "3.1非遗数字资源描述的理论基础 分类与分类体系研究": "True",
    "3.2非遗数字资源的规范化描述- -元数据方案": "True",
    "3.3非遗数字资源内容的语义表达- -本体构建": "True",
    "3.3.1 对现有成熟本体的借鉴与复用为保证本体的规范化，在": "True",
    "3.3.2 基于非遗项目的领域本体或应用本体构建由于非遗数字资源中包含": "True",
    "翟姗姗,刘齐进,白阳.面向传承和传播的非遗数字资源描述与语义揭示研究综述 [.图书情报工作 $, 2 0 1 6 , 6 0 \\bigl ( 2 \\bigr ) : 6 - 1 3$ ，21.": "False",
    "4 面向知识传播的非遗数字资源语义 揭示研究": "True",
    "4.1 非遗数字化资源中主题内容揭示及隐性知识转换": "True",
    "4.1.1 传承人及其数字化研究传承人是非遗项目重要的承载者和传递者，承担着传承、传授、总结和整理传统技艺和艺能的重要作用7-39。": "True",
    "4.1.2 突破活动流变性制约的关键事件及历史演化研究音乐、舞蹈、戏剧、曲艺等表演艺术需要活态的人在动态表现中完成，": "True",
    "4.1.3实现非遗整体性保护的文化空间数字化研究": "True",
    "4.2非遗数字资源知识单元关联揭示": "True",
    "国書情根工作": "False",
    "4.3主题内容驱动下的非遗知识可视化表达": "True",
    "5 探索与展望": "True",
    "5.1研究局限": "True",
    "翟姗姗,刘齐进，白阳.面向传承和传播的非遗数字资源描述与语义揭示研究综述『].图书情报工作 $, 2 0 1 6 , 6 0 \\bigl ( 2 \\bigr ) : 6 - 1 3$ ，": "False",
    "5.2非遗数字资源描述与语义揭示的多维度研究框架总体来说，当前非遗领域的数字资源描述的导向": "True",
    "6结语": "True",
    "参考文献：": "References",
    "翟姗姗,刘齐进,白阳.面向传承和传播的非遗数字资源描述与语义揭示研究综述⑴.图书情报工作 $, 2 0 1 6 , 6 0 \\bigl ( 2 \\bigr ) : 6 - 1 3$ ，": "References",
    "作者贡献说明：": "False",
    "Research on Categorization of Social Tags Applied to Images for": "False",
    "Museum Oriented to User Image Descriptions": "False",
    "1 School of Information Management": "False",
    "(上接第13页)": "False",
    "Research Review on the Digital Resources Description and Semantic Reveal About Intangible Cultural Heritage for Inheritance and Communication": "False"
}