{
    "西南边疆民族地区国家综合档案馆特色档案资源整合与服务现状、问题及对策": "True",
    "Current Status, Problems and Countermeasures of the Integration and Service of the Characteristic Archives Resources of the National Comprehensive Archives in the Southwest Frontier Minority Areas": "True",
    "1引言": "True",
    "2样本选择及方法": "True",
    "2.1文献研究": "True",
    "2.2网络调查": "True",
    "2.3实地调查及电话访谈": "True",
    "3西南边疆民族地区国家综合档案馆特色档案资源整合与服务调查": "True",
    "3.1广西地市级以上国家综合档案馆": "True",
    "3.1.1广西省级综合档案馆": "True",
    "3.1.2广西地市级综合档案馆": "True",
    "3.2云南地市级以上国家综合档案馆": "True",
    "3.2.1云南省级综合档案馆": "True",
    "3.2.2云南地市(州)级综合档案馆": "True",
    "3.3西藏地市 (州)级以上国家综合档案馆": "True",
    "3.3.1西藏省级综合档案馆": "True",
    "3.2.2西藏地市(地区)级综合档案馆": "True",
    "4存在的主要问题": "True",
    "4.1对地方特色档案资源的挖掘不充分": "True",
    "4.2整合与服务局限于机构内部": "True",
    "4.3整合与服务的目的不明确": "True",
    "4.4对技术的应用较为保守": "True",
    "5对策与建议": "True",
    "5.1全面调查研究，切实掌握资源的分布与现状": "True",
    "5.2做好顶层设计,推进跨区域跨部门协作": "True",
    "5.3构建平台，实现资源共建共享": "True",
    "5.4强化绩效评估，保障工作有效落实": "True",
    "5.5突出公共文化功能，与区域文化发展深度融合": "True",
    "参考文献": "References"
}