{
    "nothing": "False",
    "我国图书在版编目研究述评": "True",
    "Treating cataloguing in publication Rationally": "True",
    "1图书在版编目概况": "True",
    "2我国图书在版编目的模式": "True",
    "3图书在版编目的正面影响": "True",
    "3.1有助于促进文献编目的规范化和标准化": "True",
    "3.2有助于促进文献编目现代化": "True",
    "3.3有助于减少分类工作量，提高分编效率": "True",
    "3.4有助于图书馆分编工作向信息服务工作转移": "True",
    "3.5有助于促进CNMARC格式的实施": "True",
    "4在版编目的负面影响": "True",
    "4.1导致分编人员依赖性强，懒于思考[3]": "True",
    "4.2导致分编人员分编水平下降,辨错能力差": "True",
    "4.3导致《中图法》的改版没有多大意义": "True",
    "4.4导致图书馆的分编细则形同虚设": "True",
    "5正确认识图书在版编目的规范化和标准化": "True",
    "6对现行图书在版编目做法的改进措施": "True",
    "参考文献：": "References",
    "2004 ": "References",
    "（上接第100页）书馆出版社,2001.": "False",
    "2005 ": "References"
}