{
    "科研智能化新趋势下知识服务的挑战与机遇：": "True",
    "Challenges and Opportunities of Knowledge Service under the New Trend of Intelligent Scientific Research": "True",
    "0引言": "True",
    "1科研智能化趋势新进展": "True",
    "1.1科学研究的新态势": "True",
    "1.2国家布局的科研战略": "True",
    "2科研智能化的总体框架": "True",
    "2.1科研场景设想—平行概念下的人机共生": "True",
    "2.2科学知识的理解与掌握": "True",
    "2.3数据驱动的科学假设生成与评估": "True",
    "2.4实验方案的自动执行": "True",
    "2.5科研数据的自动获取、规范与存储": "True",
    "2.6科技文本的自动形成": "True",
    "3科研智能化驱动的知识服务新机遇": "True",
    "3.1知识服务新机遇": "True",
    "3.1.1科研数据基础设施的建设": "True",
    "3.1.2科研数据推理平台建设": "True",
    "3.1.3科研数据统一描述框架的规范": "True",
    "3.2讨论与思考": "True",
    "3.2.1重新定义知识发现": "True",
    "3.2.2新型的人机共生科研生态": "True",
    "4结束语": "True",
    "参考文献": "References",
    "（上接第181页）": "False",
    "12 (1)": "False"
}