{
    "国内图书馆与MOOC相关问题研究综述": "True",
    "郭军": "True",
    "Review of Research on Issues Related to Domestic Libraries and MOOC": "True",
    "1文献统计与分析": "True",
    "1.1发表时间及数量分析": "True",
    "1.2文献来源分析": "True",
    "·研究综述·": "False",
    "1.3作者及被引频次分析": "True",
    "1.4主题分析": "True",
    "2国内图书馆与MOOC相关问题的主要研究内容": "True",
    "2.1MO0C 理念引入与图书馆MOOC 实践经验介绍": "True",
    "2.1.1 M00C 理念引入": "True",
    "2.1.2图书馆MO0C实践经验介绍": "True",
    "2.2MOOC环境下图书馆及图书馆员的$^ { 6 6 } 2 + 2$ ”型角色定位": "True",
    "2.3MOOC环境下的图书馆服务创新": "True",
    "2.4MOOC环境下的信息素养教育": "True",
    "2.5MO0C环境下的版权服务": "True",
    "2.6MO0C平台技术支持与优化": "True",
    "3当前国内图书馆与MOOC相关问题研究的特点及存在的主要问题": "True",
    "3.1研究特点": "True",
    "3.1.1研究视角从单一切入过渡到多维综合": "True",
    "3.1.2研究内容从对表征现象分析过渡到对内在规律探究": "True",
    "3.1.3研究思路从借鉴国外理论成果与实践经验过渡到本土化探索": "True",
    "3.1.4研究方法从理论定性分析过渡到实证案例研究": "True",
    "3.2存在问题": "True",
    "3.2.1MOOC环境下的图书馆学基础理论研究匮乏": "True",
    "3.2.2基于图书馆MOOC实践的实证研究薄弱": "True",
    "3.2.3图书馆与MO0C融合的主要路径定位偏颇": "True",
    "3.2.4图书馆参与 MOOC本土化的理论与实践尚处于初步探讨层面": "True",
    "4今后研究建议": "True",
    "4.1注重MOOC环境下的图书馆学基础理论研究": "True",
    "4.2加强图书馆参与MO0C 本土化的实证研究": "True",
    "4.3立足馆藏资源和实体空间助力MOOC 的推广与普及": "True",
    "4.4协调推进高校图书馆和公共图书馆与MOOC相融合": "True"
}