{
    "讲故事活动在图书馆的历史、现状与发展": "True",
    "[关键词]公共图书馆少儿图书馆少儿图书馆员讲故事少儿服务": "False",
    "1“讲故事”与图书馆解不开的渊源": "True",
    "1.1图书馆界讲故事的先驱": "True",
    "1.2讲故事活动在图书馆的实践历程": "True",
    "2时代变革中的讲故事活动": "True",
    "2.1扩大了参与讲故事活动的少儿数量": "True",
    "2.2将音乐应用在讲故事活动中": "True",
    "2.3科学技术的发展极大地拓展了讲故事活动的方式": "True",
    "3我国讲故事活动的现状": "True",
    "3.1 名师指点，注重技巧，区别年龄。": "True",
    "3.2内容丰富，生动活泼，贴近少儿。": "True",
    "3.3社会参与，广泛合作，创造共赢。": "True",
    "4讲故事活动的创新": "True",
    "4.1更新观念，提高对讲故事活动重要性的认识。": "True",
    "4.2加强馆际合作，充分发挥行业协会的作用。": "True",
    "4.3 以少儿为中心，打造丰富有趣的“讲故事\"品牌。": "True",
    "参考文献：": "References",
    "[作者简介]": "False"
}