{
    "●曲静涛": "False",
    "书后索引在我国的编制现状及问题探究": "True",
    "1书后索引编制意义及常见形式": "True",
    "1.1书后索引的通俗理解": "True",
    "1.2书后索引功用": "True",
    "1.3书后索引形式。": "True",
    "1.3.1词语索引": "True",
    "1.3.2符号索引": "True",
    "1.3.3数字索引": "True",
    "1.3.4字顺索引": "True",
    "1.3.5分类索引": "True",
    "2我国书后索引现状": "True",
    "3制约书后索引发展的社会因素及相应措施": "True",
    "3.1人们的文化素养不高，缺乏情报检索意识。": "True",
    "3.2要改变文献使用习惯，扩大文献揭示手段。": "True",
    "3.3应利用先进技术编制索引。": "True",
    "参考文献": "References",
    "1 ": "References",
    "（上接第71页）": "False",
    "金融危机": "False",
    "中等专业教育": "False"
}