{
    "国内外信息偶遇研究的回顾与展望聂勇浩李霞": "True",
    "【关键词】信息偶遇信息行为信息获取": "True",
    "0 引言": "True",
    "1信息偶遇的概念": "True",
    "2信息偶遇的过程": "True",
    "3信息偶遇的发生机制": "True",
    "4促进信息偶遇的策略": "True",
    "4.1促进信息偶遇的环境设计": "True",
    "4.1.1 尽可能创建随机的信息间链接": "True",
    "4.1.2 创新内容和展现形式": "True",
    "4.1.3 一个环境设计的基本策略": "True",
    "4.2促进信息偶遇的实践案例": "True",
    "5结语与展望": "True",
    "注释": "References",
    "[14]潘曙光．信息偶遇研究[D]．重庆：西南大学，2010： $4 - 6 .$": "References",
    "[16]马翠嫦，曹树金．信息分散下的信息行为——基于国外图书情报学领域跨学科研究的回顾[J].中国图书馆学报，2014（1)：60—72.": "References",
    "[33]王娩娩，张家年．信息偶遇理论视角下“偶遇学习”模型构建[J].知识管理论坛，2017（1)：69－76.": "References",
    "35]蒋冠裙．浅议新媒体时代如何促进读者信息偶遇[J].图书馆研究，2015（5）：116—118.": "References",
    "[36]袁红，王志鹏．数字图书馆利用中信息偶遇现象研究[J]．图书情报工作，2014（17)：104—111，135.": "References",
    "[40]田立忠，俞碧飚．科研人员信息偶遇的影响因素研究[J]．情报科学，2013（4）： $6 9 - 7 5$ ，83.": "References",
    "[44]田梅，张军亮，刘喜文.移动互联网信息偶遇行为演进动力机制分析：个体认知视角[J].图书馆学研究，2018（6）：55一58，73.[45]杨敏，谢阳群，谢笑．社交媒体软件的信息偶遇研究[J]．图书馆学研究，2016（6)：65－68，9.": "References",
    "[50]胥文娟，黄丽霞.基于信息偶遇的高校图书馆OPAC功能拓展研究[J].图书馆理论与实践，2017（9）：99－102.": "References",
    "[56]阳玉堃，黄椰曼．社交网络环境下用户信息偶遇行为影响因素研究[J].数字图书馆论坛，2017（6）：65—72.": "References",
    "聂勇浩中山大学资讯管理学院副教授，硕士生导师。主要研究方向：信息服务、信息行为。": "False",
    "李霞云南大学国际学院教师。主要研究方向：信息服务、信息行为。": "False",
    "(上接第16页）": "False"
}