{
    "移动社交媒体环境下用户错失焦虑症(FoMO)的研究回顾与展望": "True",
    "1引言": "True",
    "移动社交媒体环境下FoMO的概念 阐述": "True",
    "2.1 文献来源": "True",
    "2.2概念界定": "True",
    "2.3概念辨析": "True",
    "2.3.1相关概念介绍": "True",
    "2.3.2 相关概念的共性与差异基于对FoMO、沉浸体验、网络/手机上瘾的概念以及文献的梳理,笔者认为三者本质上的共性在于用户对技术、产品、媒介等产生的依赖性(见图1）。": "True",
    "3FoMO的测量量表": "True",
    "4 移动社交媒体环境下FoMO的影响因素": "True",
    "4.1个体特征因素": "True",
    "4.1.1 人口统计学特征与FoMO人口统计学特征": "True",
    "4.1.2 人格特质与FoMO著名心理学家G．W．All-port将人格定义为“个体内部的心身系统的动力组织，": "True",
    "4.2心理因素": "True",
    "4.2.1 自我决定理论与FoMO": "True",
    "赵宇翔，张轩慧，宋小康.移动社交媒体环境下用户错失焦虑症(FoMO)的研究回顾与展望[.图书情报工作,2017,61(8) :133 -144.": "False",
    "4.2.2 归属需求理论与FoMO归属需求": "True",
    "4.2.3 沉浸理论与FoMO沉浸感": "True",
    "4.3技术因素": "True",
    "4.3.1 技术接受模型及其扩展模型技术接受模型（technology acceptancemodel,TAM)": "True",
    "4.3.2 创新扩散理论创新扩散理论(innovation dif-fusion theory,IDT）目前被广泛应用在信息系统研究中,用以解释用户对新技术的接受与采纳。": "True",
    "移动社交媒体环境下FoMO研究的前沿展望": "True",
    "5.1移动社交媒体环境下FoMO的测量量表开发": "True",
    "5.2构建移动社交媒体环境下FoMO 影响因素的实证模型": "True",
    "5.3从移动社交类App 开发的角度考察 App 设计与用户FoMO的关系": "True",
    "5.4探究移动社交媒体环境下FoMO的研究在教育及公共安全等领域的应用": "True",
    "5.5开展多方法研究": "True",
    "6结语": "True",
    "参考文献：": "References"
}