{
    "图書与情報": "False",
    "北欧信息素养教育进展": "True",
    "The Advances of Information Literacy Instruction in Nordic": "True",
    "1北欧信息素养教育的发展背景": "True",
    "目，旨在研究网络搜索、信息素养和学习之间的关系，并揭示在网络信息环境中信息素养和学习之间的相互作用。": "True",
    "2北欧信息素养组织机构及其活动": "True",
    "2.1北欧信息素养组织机构": "True",
    "2.2北欧信息素养学术活动": "True",
    "2.2.1“创造知识(CK)\"国际会议": "True",
    "2.2.2北欧信息素养学术会议[26]和夏令营[27]": "True",
    "3北欧高校信息素养教育实践": "True",
    "3.1样本高校信息素养教育概况": "True",
    "3.1.1哥本哈根大学(University of COPENHAGEN,CU)": "True",
    "3.1.2赫尔辛基大学(University of Helsinki,UH)": "True",
    "3.1.3查尔姆斯理工大学（Chalmers University ofTechnology,CUT)": "True",
    "3.1.4俾尔根大学(University of Bergen,BU)": "True",
    "3.2调查分析": "True",
    "3.2.1信息素养教育方式": "True",
    "3.2.2信息素养教育的层次": "True",
    "3.2.3信息素养项目的实施": "True",
    "3.2.4信息素养的测评": "True",
    "5结语": "True",
    "程设计、在线教育平台构建，北欧国家在信息素养教育方面取得了很大进展。": "True",
    "参考文献：   \n[1] HIGH LEVEL COLLOQUIUM ON INFORMATION LITERACY AND LIFELONG LEARNING.BeaCons of the information literacy :the Alexandria proclamation on information literacy and lifelong learning [EB/OL].[2011- 10-01].http //www.ceris.cnr.it/Basili/EnIL/Alex.html.   \n[2] Annette Skov，Hell Skarbak.Fightingan uphill attle : teaching information literacy in Danish institutions of higher education [] .Library Review,2003,52 ( 326- 332.   \n[3] Rektorkollegiets Biblioteksudvalg.Viden til tiden [R/OL]. [2011-10-01].http //www.rektorkollegiet.dk/fileadmin/ user_upload/downloads/videntiltiden.pdf.   \n[4] Kaisa Sinikara,Leena Ja rvela inen.Information literacy development in Finland [].Library Review,2003,52 (： 333-339.   \n[5] Ministry of Education and Culture. Education and Research 2003-2008 [EB/OL].[2011-10-01].htp /www. minedu.fi/OPM/Julkaisut/2004/koulutuksen_ja_tutkimuksen_kehittamissuunnitelma_2003-2008?lang=en.   \n[6 University of Helsinki. Information Literacy Curriculum Project 2004-2006 [...]": "References"
}