{
    "1999—2008年我国图书馆评估研究述评-对图书馆评估研究论文的计量分析": "True",
    "金胜勇贾东琴": "True",
    "1文献调研": "True",
    "1.1论文年代分布": "True",
    "1.2载文的著者分布": "True",
    "1.3载文的期刊分布": "True",
    "1.4论文主题分布": "True",
    "2图书馆评估的主要研究内容分析": "True",
    "2.1图书馆评估综合理论": "True",
    "2.2图书馆评估主体": "True",
    "2.3图书馆评估客体": "True",
    "2.4图书馆评估指标体系": "True",
    "2.5图书馆评估方法": "True",
    "3国内图书馆评估研究存在的问题及发展趋势": "True",
    "3.1国内图书馆评估研究存在的问题": "True",
    "3.2国内图书馆评估研究发展趋势": "True",
    "3.2.1图书馆评估理论逐步深化": "True",
    "3.2.2图书馆评估机制趋向规范": "True",
    "4结语": "True",
    "参考文献：": "References"
}