{
    "中国预印本服务系统运行现状分析及发展策略研究": "True",
    "高洁": "True",
    "1引言": "True",
    "2.3 文章提交用户登录预印本系统后,可以根据提示，填写文章的相关信息，并选择好相应的类型，将文章上传到系统中。": "True",
    "2.4 我的文章": "True",
    "2系统功能": "True",
    "2.1 分类浏览预印本系统中": "True",
    "2.2文章检索通过输入检索词,用户可以根据不同的专业需要，选择所需学科类型，进行检索浏览。": "True",
    "2.5 国外预印本门户(SINDAP）国外预印本内户(SINDAP)子系统": "True",
    "3系统运行现状分析": "True",
    "3.1 文章类型中国预印本服务系统中的文章分为五大类，每一类下又分成多个二级子类，用户可以按不同的学科分类，将文章存放到相应的类型中。": "True",
    "3.2 文章数量中国预印本系统于2004年开通，系统运行一直处于平稳状态，截至2010 年12月31日共有文章3110篇。": "True",
    "3.3 注册用户中国预印本系统开通时作为一个独立的系统,用户可以在": "True",
    "4未来发展": "True",
    "参考文献：": "References",
    "(上接第118页)": "False"
}