{
    "信息安全技术与产品发展趋势分析": "True",
    "Research on the Development Tendency of the Information Security Technology & Products": "True",
    "1信息化社会的信息安全及问题": "True",
    "1.1信息安全是人类信息化社会的基本需求": "True",
    "1.2信息安全的技术缺陷及威胁": "True",
    "1.3信息加密技术是信息安全的核心技术": "True",
    "2信息加密技术面临严峻挑战": "True",
    "2.1信息加密技术的应用对象": "True",
    "2.2信息加密技术在信息安全技术中的优势地位": "True",
    "2.3现有的加密技术存在致命的缺陷": "True",
    "3信息加密技术的关键是随机数产生方法": "True",
    "3.1信息加密系统及其安全要素": "True",
    "3.2随机数在加密系统中的关键性作用": "True",
    "4信息安全技术的突破方向": "True",
    "4.1理论上需要产生基于真随机数的信息加密技术": "True",
    "4.2应用上需要解决与相关技术的配套": "True",
    "5以信息加密技术为核心的相关产品开发方向": "True",
    "5.1个人信息安全系统": "True",
    "5.1.1最高可用性要解决": "True",
    "5.1.2最高安全性要解决": "True",
    "5.1.3最高监控性要解决": "True",
    "5.2企业级信息保密平台": "True",
    "5.2.1 平台特点": "True",
    "5.2.2平台的开发思想": "True",
    "5.3信息加密技术的中间件产品": "True",
    "6信息安全的后续技术与产品拓展领域展望": "True",
    "6.1技术发展路线": "True",
    "6.2从数据加工的角度看加密技术可能的应用空间": "True",
    "参考文献": "References",
    "1 ": "References"
}