{
    "我国信息用户需求和信息行为分析研究综述": "True",
    "1信息用户需求和信息行为分析研究的发文情况": "True",
    "1.1在所有学科领域": "True",
    "1.2在图书情报学领域": "True",
    "1.3图书情报领域与非图书情报领域发文量统计比较": "True",
    "2信息用户需求和信息行为分析研究的内容": "True",
    "2.1信息用户、信息需求和信息行为的概念": "True",
    "2.1.1信息用户的概念": "True",
    "2.1.2信息需求的概念": "True",
    "2.1.3信息行为的概念": "True",
    "2.2信息需求和信息行为的特点": "True",
    "2.2.1信息需求的特点": "True",
    "2.2.2用户信息行为特征": "True",
    "3信息用户需求和信息行为分析研究的发展方向": "True",
    "[参考文献]": "References",
    "The analysis on the information user 's demand and Information Behavior in Our Country": "False",
    "SUN Lin-shan": "False"
}