{
    "算法偏见概念、哲理基础与后果的系统回顾": "True",
    "贾诗威闫慧": "True",
    "A Systematic Review of Concept,Philosophy Foundation and Impacts of Algorithmic Bias": "True",
    "ABSTRACT": "True",
    "KEY WORDS": "True",
    "0引言": "True",
    "1研究方法": "True",
    "1.1检索策略": "True",
    "1.2文献纳人/排除标准": "True",
    "1.3质量评估": "True",
    "2算法偏见的内涵与外延": "True",
    "2.1算法偏见的内涵": "True",
    "2.2外延标准一：算法偏见来源": "True",
    "2.3外延标准二：算法偏见对象": "True",
    "2.4算法偏见的概念框架": "True",
    "(1)人类智能系统内的偏见链": "True",
    "(2)人工智能系统内的偏见循环圈": "True",
    "(3)人类智能系统到人工智能系统的偏见作用路径": "True",
    "3算法偏见的哲理反思": "True",
    "3.1功能主义与算法偏见": "True",
    "3.2冲突论与算法偏见": "True",
    "3.3还原论与算法偏见": "True",
    "3.4马克思主义与算法偏见": "True",
    "4算法偏见的后果": "True"
}