{
    "国外技术创新中情报的作用研究综述": "True",
    "A Foreign Literature Review on the Role of Intelligence in Technological Innovation": "True",
    "1引言": "True",
    "2 技术创新中情报的地位和作用": "True",
    "2.1技术创新中情报的地位": "True",
    "2.2 技术创新中情报的作用": "True",
    "3情报类型与技术创新类型的匹配关系": "True",
    "3.1不同的情报类型在技术创新中的作用": "True",
    "3.2不同技术创新类型中情报的作用": "True",
    "4结语": "True",
    "参考文献": "References",
    "1 O'Meara,J. T. Selecting profitable products[J].Harvard Business Review,1961,(39):83-89.   \n2Schlossberg,H.Fear of failure stifles product development[J].Marketing News,1990,24 (10):1- 16.   \n3 Gourville,J. T.Eager sellers and stony buyers: Understanding the psychology of new-product adoption[J]. Harvard Business Review,2006,84 (6) :98-106.   \n4 Tatikonda M.V.，Rosenthal St.R.Sucessfull execution of product development projects: Balancing firmness and flexibility in the innovation process[Jl.Journal of Operations Management,2000,18(4):401-425.   \n5Dillon,K.I think of my failures as a gift[J].Harvard Business Review,2011,89(4):86-89.   \n6Alberto Silva.What Can We Learn From Great Business Leaders?": "References",
    "（上接第148页）": "False",
    "Toward Scalable Systems for Big Data Analytics:A Technology TutorialJ].IEEE Access,2014,2: 652-687.   \n16Liu YL,Han SF,Wang SH,Liu GY.On Big Data Analytics for Greener and Softer RAN[J].IEEE Access,2015,3: 3068-3075.   \n17Muller O,Junglas I,et al. Utilizing big data analytics for information systems research: challenges,promises and guidelines[J].European Journal of Information Systems,2016,25 (4): 289-302.   \n18Franke B,Plante JF,et al. Statistical Inference,Learning and Models in Big Data[J].Internationl Statistical Review,2016, 84(3):371-389.   \n19WangH, Xu Z S,Fujita H,Liu S S. Towards felicitous decision making:An overview on challenges and trends of Big Data[J].Information Sciences,2016,367 :747-765.   \n20 Assuncao M D, Calheiros R N,et al. Big Data computing and clouds: Trends and future directions[Jl.Journal of Parallel and Distributed Computing,2015,79-80: 3-15.   \n21 Chen EE,Wojcik SP.A Practical Guide to Big Data Research in Psychologyl].Psychological Methods,2O16,21 (4): 45...": "False"
}