{
    "nothing": "False",
    "OpenDOAR研究述评": "True",
    "1OpenDOAR介绍与分析": "True",
    "1.1OpenDOAR 简介": "True",
    "1.2OpenDOAR的收录及排除标准": "True",
    "1.3摇OpenDOAR分析研究": "True",
    "2我国的开放获取知识库实践": "True",
    "2.1OpenDOAR收录的我国开放获取知识库": "True",
    "OpenDOAR收录的我国大陆地区的知识库共有4个：": "True",
    "1 ）Sharing Environmental & Ecological Knowledge Space（中国西部环境与生态科学数据中心）。": "True",
    "2 ）Xiamen University Institutional Repository （厦内大学）。": "True",
    "3 ）Knowledge Repository of National Science Library,CAS（中国科学院)。": "True",
    "4 ）Library and Information Science Institutional Reposito-ry（福建师范大学）。": "True",
    "2.2国内其他开放获取知识库实践": "True",
    "3OpenDOAR对我国开放获取知识库建设的启示": "True",
    "参考文献": "References"
}