{
    "nothing": "False",
    "高校图书馆信息共享空间的研究现状及对策分析": "True",
    "Research Status and Countermeasures of the University Library Information Commons": "True",
    "1 IC的概念及特点": "True",
    "1.1 IC 的概念": "True",
    "1.2IC 的特点": "True",
    "2 IC的构成、实现方法与模式": "True",
    "2.1 IC 的构成": "True",
    "2.2IC 的实现方法": "True",
    "2.3IC 的模式": "True",
    "3IC国内外研究现状": "True",
    "3.1 IC 国外研究现状": "True",
    "3.2IC 国内研究现状": "True",
    "3.2.1 IC内作者及发文情况 中国知网https": "True",
    "（1）论文年代分布": "True",
    "（2）论文作者分布": "True",
    "3.2.2IC 的理论与建设研究情况": "True",
    "3.3IC目前研究热点": "True",
    "3.3.1 IC 的评价问题": "True",
    "3.3.2知识产权问题": "True",
    "3.3.3开放存取": "True",
    "3.3.4知识共享空间": "True",
    "3.3.5图书馆2.0": "True",
    "4高校构建IC的几点建议": "True",
    "4.1转变图书馆服务理念，全面提高馆员素质": "True",
    "4.2加强信息资源建设，提升IC 构建新层次": "True",
    "4.3拓宽经费投资渠道，实行经费补贴政策": "True",
    "4.4加强管理运行和技术保障措施": "True",
    "4.5加强图书馆IC构建宣传，依法构建高校图书馆IC": "True",
    "参考文献": "References",
    "（上接第87页）": "False"
}