{
    "网络口碑传播研究综述": "True",
    "1网络口碑内涵": "True",
    "2网络口碑传播动机研究": "True",
    "3网络口碑传播信息研究": "True",
    "3.1 网络口碑类型国内外很多学者把口碑分为两种类型：正面口碑和负面口碑。": "True",
    "3.2 网路口碑信息特性Lynch 强调,在决定": "True",
    "4网络口碑传播效应研究": "True",
    "5网络口碑传播管理研究": "True",
    "5.1 增加消费者的产品知识和体验消费者": "True",
    "5.2 加强虚拟社区的可信度网络口碑传播与传统口碑传播的区别": "True",
    "5.3 意见领袖管理企业要进行网络口碑营销，应该寻找到能够让受众觉得可靠的、可以信赖的口碑传播者，鼓励和引导": "True",
    "5.4 负面口碑管理基于对风险预期的考虑，消费者对于负面口碑更为留意。": "True",
    "6消费者个体差异研究": "True",
    "6.1 关系强度口碑传播者与接收者之间的关系强度": "True",
    "6.2 信任在网络购物和网络忠诚领域的研究": "True",
    "6.3 感知风险在1960 年美国营销协会第43届年会上，哈佛大学的Bauer首次把“感知风险”（per-ceivedrisk)的概念从心理学延伸到市场营销学的研究领域。": "True",
    "6.4 网络涉入 涉入(Involvement)理论最早": "True",
    "6.5 专业性在网络口碑传播中,传播者": "True",
    "7结束语": "True",
    "参考文献": "References",
    "（上接第138页）": "False",
    "4结论": "False"
}