{
    "我国图书馆绩效评价研究综述何琳彭小平": "True",
    "【摘要】在分析我国图书馆绩效评价研究现状和特点的基础上，从概述性研究、国外图书馆绩效评价研究、评价指标体系、评价方法和模型、图书馆联盟绩效评价、评价具体内容等方面介绍了我国图书馆绩效评价研究的主要内容，指出了研究的不足和今后研究的趋势。": "True",
    "【关键词】图书馆绩效评价绩效评估综述": "True",
    "1图书馆绩效评价研究现状和特点": "True",
    "2主要研究内容": "True",
    "2.1概述性研究": "True",
    "2.2国外图书馆绩效评价研究": "True",
    "2.3图书馆绩效评价指标体系的研究": "True",
    "2.4图书馆绩效评价方法和模型": "True",
    "2.5图书馆联盟的绩效评价研究": "True",
    "2.6图书馆绩效评价具体内容方面的研究": "True",
    "2.6.1图书馆人力资源绩效评价研究": "True",
    "2.6.2数字图书馆和图书馆数字资源绩效评价研究": "True",
    "2.6.3图书馆业务工作绩效评价研究": "True",
    "2.6.4图书馆服务绩效评价研究": "True",
    "3当前研究存在的不足及趋势分析": "True",
    "3.1理论研究有待深化，并加强对实践的指导作用": "True",
    "3.2研究方法有待改进，注重定量分析和实证研究": "True",
    "3.3研究内容不平衡，需加强对图书馆业务工作绩效和服务绩效评价的研究": "True",
    "注释": "References",
    "3.3.3确定目标评价基础上的新的目标": "False",
    "4结束语": "False",
    "[10］白清礼.论图书馆联盟的有效沟通．图书馆学研究，2009(4)：13-16": "References"
}