{
    "数字时代知识发现海牙宣言》述评 \\*": "True",
    "■孙益武": "True",
    "导言": "True",
    "2《海牙宣言》的内容": "True",
    "3《海牙宣言》的背景": "True",
    "3.1内容开放日益成为数据时代主旋律": "True",
    "3.1.1 开放获取运动的发展根据学术出版与学术资源联盟（SPARC）的解释，开放获取": "True",
    "3.1.2 国际社会倡导开放数据在国际层面，国家政府机构以数据开放展开数据与信息分享的重要议题，在世界范围内掀起一股保障公民获取数据的浪潮。": "True",
    "3.2《宣言》的制度背景": "True",
    "3.2.1 WIPO国际协调的实践与局限2007年10月，WIPO通过了": "True",
    "3.2.2IFLA积极推动内容挖掘版权例外的国际协调": "True",
    "3.2.3 内容挖掘版权例外的国家实践2011年5月，英国学者": "True",
    "4《海牙宣言》核心议题的解读": "True",
    "4.1阅读权与挖掘权": "True",
    "4.2数据库权利与知识发现": "True",
    "4.3合同自由与法定例外": "True",
    "5《海牙宣言》的评价": "True",
    "5.1为制定国际条约做准备，与WIPO版权立法协调保持互动": "True",
    "5.2为软法协调树立典范，积极意义和局限性并存": "True",
    "6《海牙宣言》对我国的启示": "True",
    "6.1《海牙宣言》的积极影响": "True",
    "6.2我国支持《海牙宣言》的立场与实践": "True",
    "参考文献：": "References",
    "Review on The Hague Declaration on Knowledge Discovery in the Digital Age": "False"
}