{
    "图书情报领域中的求助行为研究述评": "True",
    "Review on Help - Seeking Behavior in Library and Information Science": "True",
    "1 基本概念": "True",
    "1.1图书情报领域求助行为的概念": "True",
    "1.2相关概念及对比分析": "True",
    "2图书情报领域求助行为的研究现状": "True",
    "2.1“问人\"现象": "True",
    "2.2参考咨询行为": "True",
    "2.2.1高校学生使用参考咨询的状况": "True",
    "2.2.2影响学生使用参考咨询服务的因素": "True",
    "2.2.3咨询方式的选择偏好和原因": "True",
    "2.3对数字图书馆帮助系统的求助行为": "True",
    "2.3.1求助状态及其影响因素": "True",
    "2.3.2求助习惯及影响因素": "True",
    "2.4社会化媒体的求助行为": "True",
    "文献。": "True",
    "3研究总结与展望": "True",
    "3.1研究内容": "True",
    "3.2研究对象与研究方法": "True",
    "3.3国内研究的不足及展望": "True",
    "求助模型，探索求助行为的影响因素，寻找提高人们有效求助的方法，改善参考咨询、帮助系统使用率低下的状况。": "True",
    "参考文献": "References"
}