{
    "nothing": "False",
    "新兴技术概念辨析及其识别方法研究进展": "True",
    "关键词：科技创新；新兴技术；识别方法；前沿技术；颠覆性技术": "True",
    "Discrimination of the Concept of Emerging Technologies and Research Progress on Its Identification Methods": "True",
    "1新兴技术相关概念辨析及特性": "True",
    "1.1新兴技术的内涵": "True",
    "1.2新兴技术的特征": "True",
    "1.3相关概念辨析": "True",
    "2现有新兴技术识别方法分析": "True",
    "2.1基于专家判断的新兴技术识别": "True",
    "2.2基于形态分析的新兴技术识别": "True",
    "2.3基于文献计量的新兴技术识别": "True",
    "2.4基于社会网络分析的新兴技术识别": "True",
    "2.5基于专利图谱分析的新兴技术识别": "True",
    "2.6基于文本挖掘的新兴技术识别": "True",
    "2.7小结": "True",
    "3新兴技术识别方法比较研究": "True",
    "4总结与展望": "True",
    "4 ）采用多源数据和多维指标相结合的方式，完善新兴技术评估体系。": "True",
    "参考文献": "References",
    "β9]汪雪锋，李兵，许幸荣，杨帆．基于形态分析法的创新导图构建及应用研究[．科学学研究，2014，32（2)：178-183，177.": "References",
    "[1]王吉武，黄鲁成，卢文光．基于文献计量的新兴技术商业化潜力客观评价研究[．现代管理科学，2008（5)：69-70.": "References",
    "[43]王培英．社会网络中的社区发现及协同过滤推荐技术研究[]．北京：北京交通大学，2016.": "References",
    "[o]黄鲁成，历妍．基于专利的技术发展趋势评价系统[]．系统管理学报，2010，19（4)：383-388.": "References",
    "52 ]": "References",
    "(上接第161页)": "False",
    "[4]彭学仕，孙春．面向倾向性分析的基于词聚类的基准词选择方法[．计算机应用研究，2011，28（1)：114-16.": "False",
    "[15] 周晓．基于互联网的情感词库扩展与优化研究[D]．沈阳：东北大学，2011.": "False",
    "[6] 王科，夏睿．情感词典自动构建方法综述[．自动化学报，2016，42(4):495-511.": "False",
    "[7] 刘若兰，年梅，玛尔哈巴·艾赛提．基于连词的维吾尔语情感词库扩展研究[．中文信息学报，2018，32（3)：49-54.": "False",
    "[8] HU M，LIU B. Mining opinion features in customer reviews[C]//Proceedings of Nineteeth National Conference on Artifi-cial Intelligence，San Jose，USA:AAAI，2004:755-760.": "False",
    "[9] 郝玫，马建峰．在线评论中基于动态窗口提取特征观点对的产品推荐模型[．系统工程理论与实践，2018，38(9):2363-2375.": "False",
    "[20] 刘臣，吉莉，唐莉．基于二分网中心节点识别的产品评论特征一观点词对提取研究[．计算机系统应用，2018，27 (11):9-16.": "False",
    "[1]DING X W，LIU B，YU P S.A Holistic Lexicon-based ap-proach to opinion mining[C]//Proceedings of The Confer-ence on Web Search And Web Data Mining（WSDM)．NewYork:ACM，2008:231-240.": "False",
    "[22] HATZIVASSILOGLOU V，MCKEOWN K R. Predicting the se-mantic orientation of adjectives[//Proc.of the 35th ACL/8th EACL，1997:174-181.": "False",
    "[23] PAGEL，BRIN S，MOTWANIR，WINOGRAD T.The pager-ank citation ranking:Bringing order to the web[R]．Techni-calReport，Stanford DigitalLibraryTechn...": "False"
}