{
    "欧美图书馆智慧服务现状调查研究贺新乾 王颖纯 刘燕权": "True",
    "【关键词】欧美公共图书馆高校图书馆智慧服务": "True",
    "0 引言": "True",
    "1相关研究综述": "True",
    "2研究设计与方法": "True",
    "2.1研究对象": "True",
    "2.2研究方法": "True",
    "3结果分析": "True",
    "3.1学科服务内容多样化": "True",
    "3.2推荐服务个性化程度较高": "True",
    "了图书馆的青睐。": "True",
    "3.3虚拟参考咨询服务评价反馈功能完善": "True",
    "3.4智慧馆员队伍强大": "True",
    "3.5移动图书馆服务开展火热": "True",
    "3.6学习空间提供充足": "True",
    "3.7特殊群体服务不可或缺": "True",
    "3.83D打印等创新服务得到重视": "True",
    "3 D打印机作为新兴的创新制造设备，虽价格昂贵，但已引起了图书馆的重视。": "True",
    "3.9注重用户隐私的保护": "True",
    "4结论与建议": "True",
    "4.1提高推荐服务个性化程度": "True",
    "4.2完善参考咨询服务评价反馈功能": "True",
    "4.3积极开展移动图书馆服务": "True",
    "4.4建立用户隐私保护机制": "True",
    "4.5重视3D打印等创新服务的开展": "True",
    "4.6培养智慧馆员": "True",
    "注释": "References",
    "伊安·约翰逊，陈旭炎．智慧城市、智慧图书馆与智慧图书馆员[．图书馆杂志，2013（1)：4-7.": "References"
}