{
    "·专题:数字资本视角下的信息行为研究·": "True",
    "数字资本理论发展透视：源起、应用与展望\\*": "True",
    "Perspective on the Development of Digital Capital Theory: Origins, Applications, and Prospects": "True",
    "1DCT的源起与发展": "True",
    "2DCT核心概念的内涵与外延": "True",
    "2.1数字资本的内涵": "True",
    "2.2数字资本的外延": "True",
    "2.1.1 数字资本与数字鸿沟": "True",
    "2.1.2数字资本与其他资本": "True",
    "3DCT变量的测量与量化": "True",
    "4DCT的应用与展望": "True",
    "4.1应用现状": "True",
    "4.1.2 DCT及其相关概念在信息行为研究中的应用": "True",
    "4.2未来展望": "True",
    "参考文献：": "References"
}